cs2star/__init__.py
cs2star/cs2star.py
cs2star/job_parser.py
cs2star-0.7.0.dist-info/METADATA
cs2star-0.7.0.dist-info/WHEEL
cs2star-0.7.0.dist-info/entry_points.txt
cs2star-0.7.0.dist-info/licenses/LICENSE
cs2star-0.7.0.dist-info/RECORD
