Metadata-Version: 2.3
Name: cs2star
Version: 0.7.0
Summary: A simple utility to convert cryosparc particle positions to relion star format.
Project-URL: homepage, https://github.com/brisvag/cs2star
Project-URL: repository, https://github.com/brisvag/cs2star
Author-email: Lorenzo Gaifas <brisvag@gmail.com>
License: GPLv3
License-File: LICENSE
Classifier: Development Status :: 3 - Alpha
Classifier: License :: OSI Approved :: GNU General Public License v3 (GPLv3)
Classifier: Natural Language :: English
Classifier: Programming Language :: Python :: 3
Classifier: Programming Language :: Python :: 3.8
Classifier: Programming Language :: Python :: 3.9
Classifier: Programming Language :: Python :: 3.10
Classifier: Programming Language :: Python :: 3.11
Requires-Python: >=3.8
Requires-Dist: click
Requires-Dist: numpy
Requires-Dist: pandas
Requires-Dist: rich
Provides-Extra: dev
Requires-Dist: black; extra == 'dev'
Requires-Dist: ipython; extra == 'dev'
Requires-Dist: pdbpp; extra == 'dev'
Requires-Dist: pre-commit; extra == 'dev'
Requires-Dist: rich; extra == 'dev'
Requires-Dist: ruff; extra == 'dev'
